mscp/__init__.py
mscp/chat2web3.py
mscp/lib.py
mscp/connectors/__init__.py
mscp/connectors/abstract_connector.py
mscp/connectors/erc7654.py
mscp/connectors/erc8004.py
mscp/connectors/abis/erc7654.json
mscp/connectors/abis/erc8004_identity.json
mscp-0.1.4.dist-info/licenses/LICENSE
mscp-0.1.4.dist-info/METADATA
mscp-0.1.4.dist-info/WHEEL
mscp-0.1.4.dist-info/top_level.txt
mscp-0.1.4.dist-info/RECORD
