Metadata-Version: 2.4
Name: mscp
Version: 0.1.4
Summary: The Model Smart Contract Protocol (MSCP) is a standard protocol that enables LLM applications to interact with EVM-compatible networks.
Author-email: rickey <hello_rickey@163.com>
License: MIT
Project-URL: Homepage, https://github.com/AmeNetwork/Model-Smart-Contract-Protocol
Project-URL: Bug Tracker, https://github.com/AmeNetwork/Model-Smart-Contract-Protocol/issues
Classifier: Programming Language :: Python :: 3
Classifier: License :: OSI Approved :: MIT License
Classifier: Operating System :: OS Independent
Requires-Python: >=3.13.2
License-File: LICENSE
Requires-Dist: web3>=7.8.0
Requires-Dist: python-dotenv>=1.0.1
Dynamic: license-file
